place/__about__.py
place/__init__.py
place/api_resource.py
place/client.py
place/exceptions.py
place/resources.py
place-0.5.5.dist-info/METADATA
place-0.5.5.dist-info/RECORD
place-0.5.5.dist-info/WHEEL
place-0.5.5.dist-info/top_level.txt
